pylint_keyword_only_args_plugin/__init__.py
pylint_keyword_only_args_plugin/checker.py
pylint_keyword_only_args_plugin/keyword_only_args.py
pylint_keyword_only_args_plugin-0.2.3.dist-info/METADATA
pylint_keyword_only_args_plugin-0.2.3.dist-info/WHEEL
pylint_keyword_only_args_plugin-0.2.3.dist-info/RECORD
